{"cameraMode":{"drawMode":0,"name":"Shaded","section":"Shading Mode"},"sceneLighting":true,"audioPlay":false,"sceneViewState":{"showFog":true,"showMaterialUpdate":false,"showSkybox":true,"showFlares":true,"showImageEffects":true,"showParticleSystems":true},"in2DMode":false,"pivot":{"x":-99.7318344116211,"y":1320.958984375,"z":1173.1844482421875},"rotation":{"x":0.06715276837348938,"y":-0.44260311126708987,"z":0.0332588367164135,"w":0.893580973148346},"size":131.65650939941407,"orthographic":false}